[{"cluster_id":0,"df_index":362,"representative_principle":"AI should provide accurate and unbiased information."},{"cluster_id":1,"df_index":594,"representative_principle":"AI should provide accurate and unbiased information."},{"cluster_id":2,"df_index":957,"representative_principle":"AI should behave in an honest and factual manner."},{"cluster_id":3,"df_index":1125,"representative_principle":"AI should provide honest and factual information."},{"cluster_id":4,"df_index":1015,"representative_principle":"AI should provide accurate information and responses."}]